veri_agents_external/__init__.py
veri_agents_external/confluence/loader.py
veri_agents_external/salesforce/api.py
veri_agents_external/salesforce/loader.py
veri_agents_external/salesforce/tools.py
veri_agents_external-0.1.2.dist-info/METADATA
veri_agents_external-0.1.2.dist-info/WHEEL
veri_agents_external-0.1.2.dist-info/RECORD
