Metadata-Version: 2.4
Name: veri-agents-external
Version: 0.1.2
Summary: Veritone Agents Toolkit: Connectors to external software
Author-email: Markus Toman <mtoman@veritone.com>, Teo Boley <tboley@veritone.com>
Requires-Python: >=3.12
Requires-Dist: veri-agents-common[langgraph]>=0.1.2
Requires-Dist: veri-agents-knowledgebase>=0.1.1
Provides-Extra: all
Requires-Dist: atlassian-python-api>=4.0.4; extra == 'all'
Requires-Dist: beautifulsoup4>=4.13.4; extra == 'all'
Requires-Dist: langchain-community>=0.3.26; extra == 'all'
Requires-Dist: markdownify>=1.1.0; extra == 'all'
Requires-Dist: simple-salesforce>=1.12.6; extra == 'all'
Requires-Dist: slack-bolt<2.0.0,>=1.20.1; extra == 'all'
Provides-Extra: confluence
Requires-Dist: atlassian-python-api>=4.0.4; extra == 'confluence'
Requires-Dist: langchain-community>=0.3.26; extra == 'confluence'
Requires-Dist: markdownify>=1.1.0; extra == 'confluence'
Provides-Extra: dev
Requires-Dist: atlassian-python-api>=4.0.4; extra == 'dev'
Requires-Dist: beautifulsoup4>=4.13.4; extra == 'dev'
Requires-Dist: langchain-community>=0.3.26; extra == 'dev'
Requires-Dist: markdownify>=1.1.0; extra == 'dev'
Requires-Dist: simple-salesforce>=1.12.6; extra == 'dev'
Requires-Dist: slack-bolt<2.0.0,>=1.20.1; extra == 'dev'
Provides-Extra: salesforce
Requires-Dist: beautifulsoup4>=4.13.4; extra == 'salesforce'
Requires-Dist: simple-salesforce>=1.12.6; extra == 'salesforce'
Provides-Extra: slack
Requires-Dist: slack-bolt<2.0.0,>=1.20.1; extra == 'slack'
